{
  "exportedAt": "2026-07-10T09:22:52.888Z",
  "finance": {
    "asOf": {
      "year": 2026,
      "month": 7
    },
    "summary": {
      "assets": 639996,
      "liabilities": 0,
      "netWorth": 639996,
      "exclApt": 355996,
      "debtRatio": 0,
      "emergencyFund": {
        "liquid": 23404,
        "covered": 8.7,
        "target": 9,
        "targetAmount": 24073,
        "ok": false
      }
    },
    "groups": [
      {
        "key": "property",
        "label": "Property",
        "section": "Assets",
        "value": 284000
      },
      {
        "key": "investments",
        "label": "Investments",
        "section": "Assets",
        "value": 154486
      },
      {
        "key": "lockedsavings",
        "label": "Locked savings",
        "section": "Assets",
        "value": 169682
      },
      {
        "key": "liquidsavings",
        "label": "Liquid savings",
        "section": "Assets",
        "value": 23404
      },
      {
        "key": "liquidity",
        "label": "Liquidity",
        "section": "Assets",
        "value": 8424
      },
      {
        "key": "credit",
        "label": "Credit",
        "section": "Liabilities",
        "value": 0
      }
    ],
    "history": [
      {
        "year": 2021,
        "month": 12,
        "netWorth": 277849,
        "exclApt": 117983
      },
      {
        "year": 2022,
        "month": 12,
        "netWorth": 294551,
        "exclApt": 133425
      },
      {
        "year": 2023,
        "month": 12,
        "netWorth": 348136,
        "exclApt": 175064
      },
      {
        "year": 2024,
        "month": 12,
        "netWorth": 443243,
        "exclApt": 224049
      },
      {
        "year": 2025,
        "month": 12,
        "netWorth": 569853,
        "exclApt": 304853
      },
      {
        "year": 2026,
        "month": 7,
        "netWorth": 639996,
        "exclApt": 355996
      }
    ],
    "projections": [
      {
        "year": 2021,
        "projected": false,
        "netWorth": 277849,
        "exclApt": 117983
      },
      {
        "year": 2022,
        "projected": false,
        "netWorth": 294551,
        "exclApt": 133425
      },
      {
        "year": 2023,
        "projected": false,
        "netWorth": 348136,
        "exclApt": 175064
      },
      {
        "year": 2024,
        "projected": false,
        "netWorth": 443243,
        "exclApt": 224049
      },
      {
        "year": 2025,
        "projected": false,
        "netWorth": 569853,
        "exclApt": 304853
      },
      {
        "year": 2026,
        "month": 7,
        "projected": false,
        "netWorth": 639996,
        "exclApt": 355996
      },
      {
        "year": 2026,
        "projected": true,
        "netWorth": 666155,
        "exclApt": 368977
      },
      {
        "year": 2027,
        "projected": true,
        "netWorth": 733680,
        "exclApt": 402327
      },
      {
        "year": 2028,
        "projected": true,
        "netWorth": 808501,
        "exclApt": 439043
      },
      {
        "year": 2029,
        "projected": true,
        "netWorth": 891432,
        "exclApt": 479485
      },
      {
        "year": 2030,
        "projected": true,
        "netWorth": 983379,
        "exclApt": 524059
      },
      {
        "year": 2031,
        "projected": true,
        "netWorth": 1085354,
        "exclApt": 573212
      },
      {
        "year": 2032,
        "projected": true,
        "netWorth": 1198483,
        "exclApt": 627444
      },
      {
        "year": 2033,
        "projected": true,
        "netWorth": 1324019,
        "exclApt": 687311
      },
      {
        "year": 2034,
        "projected": true,
        "netWorth": 1463361,
        "exclApt": 753432
      },
      {
        "year": 2035,
        "projected": true,
        "netWorth": 1618067,
        "exclApt": 826496
      },
      {
        "year": 2036,
        "projected": true,
        "netWorth": 1789873,
        "exclApt": 907271
      },
      {
        "year": 2037,
        "projected": true,
        "netWorth": 1980715,
        "exclApt": 996613
      }
    ],
    "projAssumptions": {
      "property": 0.115,
      "investments": 0.07,
      "lockedsavings": 0.12,
      "liquidsavings": 0.03,
      "liquidity": 0.02,
      "credit": 0
    },
    "targetAmount": 1000000
  },
  "portfolio": {
    "summary": {
      "totalValue": 150919,
      "totalCost": 104948,
      "totalGain": 45971,
      "totalGainPct": 43.8
    },
    "positions": [
      {
        "stock": "Allianz",
        "ticker": "ALV.DE",
        "brokers": "Equate+, Degiro, Lightyear",
        "shares": 58.193,
        "price": 423.9,
        "value": 24668,
        "cost": 8971,
        "gain": 15697,
        "gainPct": 175,
        "yieldPct": 0
      },
      {
        "stock": "KeyCorp",
        "ticker": "KEY",
        "brokers": "Degiro",
        "shares": 280,
        "price": 20.2,
        "value": 5656,
        "cost": 3434,
        "gain": 2223,
        "gainPct": 64.7,
        "yieldPct": 0
      },
      {
        "stock": "Wolters Kluwer",
        "ticker": "WKL.AS",
        "brokers": "Lightyear",
        "shares": 94,
        "price": 59.9,
        "value": 5631,
        "cost": 5506,
        "gain": 125,
        "gainPct": 2.3,
        "yieldPct": 3.8
      },
      {
        "stock": "Citigroup",
        "ticker": "C",
        "brokers": "Degiro",
        "shares": 40,
        "price": 122.05,
        "value": 4882,
        "cost": 2007,
        "gain": 2875,
        "gainPct": 143.2,
        "yieldPct": 0
      },
      {
        "stock": "McDonald's",
        "ticker": "MCD",
        "brokers": "Degiro",
        "shares": 20,
        "price": 241.79,
        "value": 4836,
        "cost": 5400,
        "gain": -564,
        "gainPct": -10.4,
        "yieldPct": 0
      },
      {
        "stock": "Johnson & Johnson",
        "ticker": "JNJ",
        "brokers": "Degiro",
        "shares": 20,
        "price": 226.58,
        "value": 4532,
        "cost": 2944,
        "gain": 1588,
        "gainPct": 53.9,
        "yieldPct": 0
      },
      {
        "stock": "Lloyds Banking Group",
        "ticker": "LLOY.L",
        "brokers": "Degiro",
        "shares": 3000,
        "price": 1.32,
        "value": 3964,
        "cost": 1491,
        "gain": 2473,
        "gainPct": 165.9,
        "yieldPct": 0
      },
      {
        "stock": "Aviva",
        "ticker": "AV.L",
        "brokers": "Degiro",
        "shares": 500,
        "price": 7.76,
        "value": 3881,
        "cost": 2440,
        "gain": 1442,
        "gainPct": 59.1,
        "yieldPct": 0
      },
      {
        "stock": "Iberdrola",
        "ticker": "IBE.MC",
        "brokers": "Broker ING",
        "shares": 178,
        "price": 20.94,
        "value": 3727,
        "cost": 2771,
        "gain": 956,
        "gainPct": 34.5,
        "yieldPct": 0
      },
      {
        "stock": "Repsol",
        "ticker": "REP.MC",
        "brokers": "Broker ING",
        "shares": 148,
        "price": 23.4,
        "value": 3463,
        "cost": 1486,
        "gain": 1978,
        "gainPct": 133.1,
        "yieldPct": 0
      },
      {
        "stock": "EPR Properties",
        "ticker": "EPR",
        "brokers": "Degiro",
        "shares": 65,
        "price": 52.09,
        "value": 3386,
        "cost": 2771,
        "gain": 615,
        "gainPct": 22.2,
        "yieldPct": 0
      },
      {
        "stock": "Realty Income",
        "ticker": "O",
        "brokers": "XTB",
        "shares": 61,
        "price": 55.24,
        "value": 3370,
        "cost": 3125,
        "gain": 245,
        "gainPct": 7.8,
        "yieldPct": 0
      },
      {
        "stock": "ACS",
        "ticker": "ACS.MC",
        "brokers": "Broker ING",
        "shares": 28,
        "price": 120,
        "value": 3360,
        "cost": 529,
        "gain": 2831,
        "gainPct": 535.3,
        "yieldPct": 0
      },
      {
        "stock": "Merlin Properties",
        "ticker": "MRL.MC",
        "brokers": "Broker ING",
        "shares": 220,
        "price": 15.04,
        "value": 3309,
        "cost": 2415,
        "gain": 894,
        "gainPct": 37,
        "yieldPct": 0
      },
      {
        "stock": "ABN AMRO Bank",
        "ticker": "ABN.AS",
        "brokers": "Lightyear",
        "shares": 78,
        "price": 38.06,
        "value": 2969,
        "cost": 2302,
        "gain": 667,
        "gainPct": 29,
        "yieldPct": 0
      },
      {
        "stock": "ING",
        "ticker": "INGA.AS",
        "brokers": "XTB",
        "shares": 103,
        "price": 28.31,
        "value": 2916,
        "cost": 2177,
        "gain": 739,
        "gainPct": 33.9,
        "yieldPct": 0
      },
      {
        "stock": "GSK",
        "ticker": "GSK.L",
        "brokers": "Degiro",
        "shares": 124,
        "price": 23.17,
        "value": 2873,
        "cost": 2073,
        "gain": 800,
        "gainPct": 38.6,
        "yieldPct": 0
      },
      {
        "stock": "Hershey",
        "ticker": "HSY",
        "brokers": "Degiro",
        "shares": 19,
        "price": 150.11,
        "value": 2852,
        "cost": 3324,
        "gain": -471,
        "gainPct": -14.2,
        "yieldPct": 0
      },
      {
        "stock": "Mapfre",
        "ticker": "MAP.MC",
        "brokers": "Broker ING",
        "shares": 640,
        "price": 4.42,
        "value": 2829,
        "cost": 1581,
        "gain": 1248,
        "gainPct": 79,
        "yieldPct": 0
      },
      {
        "stock": "Endesa",
        "ticker": "ELE.MC",
        "brokers": "Broker ING",
        "shares": 70,
        "price": 38.77,
        "value": 2714,
        "cost": 1482,
        "gain": 1232,
        "gainPct": 83.2,
        "yieldPct": 0
      },
      {
        "stock": "Logista",
        "ticker": "LOG.MC",
        "brokers": "Broker ING",
        "shares": 80,
        "price": 33.82,
        "value": 2706,
        "cost": 2196,
        "gain": 510,
        "gainPct": 23.2,
        "yieldPct": 0
      },
      {
        "stock": "Sabadell",
        "ticker": "SAB.MC",
        "brokers": "Broker ING",
        "shares": 800,
        "price": 3.21,
        "value": 2568,
        "cost": 2554,
        "gain": 14,
        "gainPct": 0.5,
        "yieldPct": 0
      },
      {
        "stock": "Inditex",
        "ticker": "ITX.MC",
        "brokers": "Broker ING",
        "shares": 46,
        "price": 55.62,
        "value": 2559,
        "cost": 2006,
        "gain": 553,
        "gainPct": 27.5,
        "yieldPct": 0
      },
      {
        "stock": "BBVA",
        "ticker": "BBVA.MC",
        "brokers": "Broker ING",
        "shares": 114,
        "price": 22.42,
        "value": 2556,
        "cost": 1360,
        "gain": 1196,
        "gainPct": 87.9,
        "yieldPct": 0
      },
      {
        "stock": "Viscofan",
        "ticker": "VIS.MC",
        "brokers": "Broker ING",
        "shares": 45,
        "price": 56.2,
        "value": 2529,
        "cost": 2664,
        "gain": -135,
        "gainPct": -5.1,
        "yieldPct": 0
      },
      {
        "stock": "National Grid",
        "ticker": "NG.L",
        "brokers": "Degiro",
        "shares": 170,
        "price": 14.58,
        "value": 2479,
        "cost": 1937,
        "gain": 541,
        "gainPct": 27.9,
        "yieldPct": 0
      },
      {
        "stock": "M&G",
        "ticker": "MNG.L",
        "brokers": "Degiro",
        "shares": 600,
        "price": 4.08,
        "value": 2449,
        "cost": 1417,
        "gain": 1032,
        "gainPct": 72.9,
        "yieldPct": 0
      },
      {
        "stock": "Sainsbury",
        "ticker": "SBRY.L",
        "brokers": "Degiro",
        "shares": 600,
        "price": 4.01,
        "value": 2407,
        "cost": 2077,
        "gain": 330,
        "gainPct": 15.9,
        "yieldPct": 0
      },
      {
        "stock": "Exxon Mobil",
        "ticker": "XOM",
        "brokers": "Degiro",
        "shares": 20,
        "price": 120.21,
        "value": 2404,
        "cost": 895,
        "gain": 1509,
        "gainPct": 168.5,
        "yieldPct": 0
      },
      {
        "stock": "Main Street Capital",
        "ticker": "MAIN",
        "brokers": "XTB",
        "shares": 53,
        "price": 45.19,
        "value": 2395,
        "cost": 2682,
        "gain": -287,
        "gainPct": -10.7,
        "yieldPct": 0
      },
      {
        "stock": "Vidrala",
        "ticker": "VID.MC",
        "brokers": "Broker ING",
        "shares": 27,
        "price": 88.2,
        "value": 2381,
        "cost": 2442,
        "gain": -60,
        "gainPct": -2.5,
        "yieldPct": 0
      },
      {
        "stock": "Chesnara",
        "ticker": "CSN.L",
        "brokers": "Degiro",
        "shares": 600,
        "price": 3.95,
        "value": 2371,
        "cost": 1909,
        "gain": 463,
        "gainPct": 24.2,
        "yieldPct": 0
      },
      {
        "stock": "Bankinter",
        "ticker": "BKT.MC",
        "brokers": "Broker ING",
        "shares": 150,
        "price": 15.2,
        "value": 2280,
        "cost": 979,
        "gain": 1301,
        "gainPct": 132.9,
        "yieldPct": 0
      },
      {
        "stock": "Van Laschot Kempen",
        "ticker": "VLK.AS",
        "brokers": "Lightyear",
        "shares": 34,
        "price": 64.4,
        "value": 2190,
        "cost": 1789,
        "gain": 400,
        "gainPct": 22.4,
        "yieldPct": 0
      },
      {
        "stock": "AbbVie",
        "ticker": "ABBV",
        "brokers": "XTB",
        "shares": 10,
        "price": 218.55,
        "value": 2185,
        "cost": 1653,
        "gain": 533,
        "gainPct": 32.2,
        "yieldPct": 0
      },
      {
        "stock": "Coca-Cola",
        "ticker": "KO",
        "brokers": "Degiro",
        "shares": 30,
        "price": 72.26,
        "value": 2168,
        "cost": 1633,
        "gain": 534,
        "gainPct": 32.7,
        "yieldPct": 0
      },
      {
        "stock": "BAE Systems",
        "ticker": "BA.L",
        "brokers": "Degiro",
        "shares": 100,
        "price": 21.61,
        "value": 2161,
        "cost": 1516,
        "gain": 645,
        "gainPct": 42.5,
        "yieldPct": 0
      },
      {
        "stock": "Rio Tinto",
        "ticker": "RIO.L",
        "brokers": "Degiro",
        "shares": 24,
        "price": 79.72,
        "value": 1913,
        "cost": 1414,
        "gain": 499,
        "gainPct": 35.3,
        "yieldPct": 0
      },
      {
        "stock": "3M",
        "ticker": "MMM",
        "brokers": "Degiro",
        "shares": 12,
        "price": 135.84,
        "value": 1630,
        "cost": 1238,
        "gain": 392,
        "gainPct": 31.6,
        "yieldPct": 0
      },
      {
        "stock": "ASML",
        "ticker": "ASML.AS",
        "brokers": "XTB",
        "shares": 1,
        "price": 1554.8,
        "value": 1555,
        "cost": 847,
        "gain": 708,
        "gainPct": 83.6,
        "yieldPct": 0
      },
      {
        "stock": "Diageo",
        "ticker": "DGE.L",
        "brokers": "Degiro",
        "shares": 86,
        "price": 17.73,
        "value": 1525,
        "cost": 2406,
        "gain": -881,
        "gainPct": -36.6,
        "yieldPct": 0
      },
      {
        "stock": "Heineken",
        "ticker": "HEIA.AS",
        "brokers": "Freedom24",
        "shares": 20,
        "price": 75.34,
        "value": 1507,
        "cost": 1454,
        "gain": 52,
        "gainPct": 3.6,
        "yieldPct": 0
      },
      {
        "stock": "Imperial Brands",
        "ticker": "IMB.L",
        "brokers": "Degiro",
        "shares": 46,
        "price": 32.14,
        "value": 1478,
        "cost": 1294,
        "gain": 185,
        "gainPct": 14.3,
        "yieldPct": 0
      },
      {
        "stock": "Global Dominion",
        "ticker": "DOM.MC",
        "brokers": "Broker ING",
        "shares": 500,
        "price": 2.88,
        "value": 1440,
        "cost": 1597,
        "gain": -157,
        "gainPct": -9.8,
        "yieldPct": 0
      },
      {
        "stock": "Western Union",
        "ticker": "WU",
        "brokers": "Degiro",
        "shares": 190,
        "price": 6.84,
        "value": 1299,
        "cost": 2282,
        "gain": -982,
        "gainPct": -43.1,
        "yieldPct": 0
      },
      {
        "stock": "Ebro Foods",
        "ticker": "EBRO.MC",
        "brokers": "Broker ING",
        "shares": 54,
        "price": 18.04,
        "value": 974,
        "cost": 983,
        "gain": -9,
        "gainPct": -0.9,
        "yieldPct": 0
      },
      {
        "stock": "Renewables Infrastructure",
        "ticker": "TRIG.L",
        "brokers": "Degiro",
        "shares": 1000,
        "price": 0.83,
        "value": 826,
        "cost": 1294,
        "gain": -468,
        "gainPct": -36.2,
        "yieldPct": 0
      },
      {
        "stock": "Global Water Resources",
        "ticker": "GWRS",
        "brokers": "XTB",
        "shares": 28,
        "price": 5.99,
        "value": 168,
        "cost": 202,
        "gain": -34,
        "gainPct": -17.1,
        "yieldPct": 0
      }
    ],
    "projections": {
      "valueGrowthRate": 0.07,
      "monthlyDeposit": 300,
      "divGrowthRate": 0.05,
      "endDate": "2040-12"
    }
  }
}